toposort.py
toposort-1.8.dist-info/LICENSE.txt
toposort-1.8.dist-info/METADATA
toposort-1.8.dist-info/WHEEL
toposort-1.8.dist-info/top_level.txt
toposort-1.8.dist-info/RECORD
