Metadata-Version: 2.1
Name: toposort
Version: 1.8
Summary: Implements a topological sort algorithm.
Author-email: "Eric V. Smith" <eric@trueblade.com>
License: Apache License Version 2.0
Project-URL: source, https://gitlab.com/ericvsmith/toposort
Classifier: Development Status :: 5 - Production/Stable
Classifier: Intended Audience :: Developers
Classifier: License :: OSI Approved :: Apache Software License
Classifier: Topic :: Software Development :: Libraries :: Python Modules
Classifier: Programming Language :: Python :: 3.8
Classifier: Programming Language :: Python :: 3.9
Classifier: Programming Language :: Python :: 3.10
License-File: LICENSE.txt
